expreport/__init__.py
expreport/script.py
expreport/data/template.docx
expreport-1.0.4.dist-info/LICENSE
expreport-1.0.4.dist-info/METADATA
expreport-1.0.4.dist-info/WHEEL
expreport-1.0.4.dist-info/entry_points.txt
expreport-1.0.4.dist-info/top_level.txt
expreport-1.0.4.dist-info/RECORD
